wyoming_piper/__init__.py
wyoming_piper/__main__.py
wyoming_piper/const.py
wyoming_piper/download.py
wyoming_piper/file_hash.py
wyoming_piper/handler.py
wyoming_piper/voices.json
wyoming_piper-2.2.1.dist-info/licenses/LICENSE.md
wyoming_piper-2.2.1.dist-info/METADATA
wyoming_piper-2.2.1.dist-info/WHEEL
wyoming_piper-2.2.1.dist-info/entry_points.txt
wyoming_piper-2.2.1.dist-info/top_level.txt
wyoming_piper-2.2.1.dist-info/RECORD
