Metadata-Version: 2.4
Name: wyoming-piper
Version: 2.2.1
Summary: Wyoming Server for Piper
Author-email: Michael Hansen <mike@rhasspy.org>
License: MIT
Project-URL: Homepage, http://github.com/rhasspy/wyoming-piper
Keywords: rhasspy,wyoming,piper,tts
Classifier: Development Status :: 3 - Alpha
Classifier: Intended Audience :: Developers
Classifier: Topic :: Multimedia :: Sound/Audio :: Speech
Classifier: Programming Language :: Python :: 3.9
Classifier: Programming Language :: Python :: 3.10
Classifier: Programming Language :: Python :: 3.11
Classifier: Programming Language :: Python :: 3.12
Classifier: Programming Language :: Python :: 3.13
Requires-Python: >=3.9
License-File: LICENSE.md
Requires-Dist: wyoming<2,>=1.8
Requires-Dist: regex>=2024.11.6
Requires-Dist: piper-tts<2,>=1.4.0
Requires-Dist: sentence-stream<2,>=1.2.0
Provides-Extra: dev
Requires-Dist: black; extra == "dev"
Requires-Dist: flake8; extra == "dev"
Requires-Dist: mypy; extra == "dev"
Requires-Dist: pylint; extra == "dev"
Requires-Dist: pytest; extra == "dev"
Requires-Dist: pytest-asyncio; extra == "dev"
Requires-Dist: build; extra == "dev"
Requires-Dist: scipy<2,>=1.10; extra == "dev"
Requires-Dist: numpy<2,>=1.20; extra == "dev"
Requires-Dist: python-speech-features<1,>=0.6; extra == "dev"
Provides-Extra: zeroconf
Requires-Dist: wyoming[zeroconf]; extra == "zeroconf"
Provides-Extra: zh
Requires-Dist: piper-tts[zh]; extra == "zh"
Dynamic: license-file
